arches_containers/__init__.py
arches_containers/main.py
arches_containers/manage.py
arches_containers/template/_6.1_/Dockerfile
arches_containers/template/_6.1_/config.json
arches_containers/template/_6.1_/docker-compose-dependencies.yml
arches_containers/template/_6.1_/docker-compose-init.yml
arches_containers/template/_6.1_/docker-compose-persist-dependencies.yml
arches_containers/template/_6.1_/docker-compose.yml
arches_containers/template/_6.1_/docker/entrypoint.sh
arches_containers/template/_6.1_/docker/env_file.env
arches_containers/template/_6.1_/docker/init-unix.sql
arches_containers/template/_6.1_/docker/settings_local.py
arches_containers/template/_6.1_/docker/supervisor.conf
arches_containers/template/_6.1_/docker/conf.d/celerybeat.conf
arches_containers/template/_6.1_/docker/conf.d/celeryd.conf
arches_containers/template/_6.1_/docker/nginx-config/default.conf
arches_containers/template/_6.1_/docker/nginx-config/default_with_pg_serv.conf
arches_containers/template/_6.1_/docker/pg_featureserv_config/pg_featureserv.toml
arches_containers/template/_6.1_/docker/pg_tileserv_config/pg_tileserv.toml
arches_containers/template/_6.2_/Dockerfile
arches_containers/template/_6.2_/config.json
arches_containers/template/_6.2_/docker-compose-dependencies.yml
arches_containers/template/_6.2_/docker-compose-init.yml
arches_containers/template/_6.2_/docker-compose-persist-dependencies.yml
arches_containers/template/_6.2_/docker-compose.yml
arches_containers/template/_6.2_/docker/entrypoint.sh
arches_containers/template/_6.2_/docker/env_file.env
arches_containers/template/_6.2_/docker/init-unix.sql
arches_containers/template/_6.2_/docker/settings_local.py
arches_containers/template/_6.2_/docker/supervisor.conf
arches_containers/template/_6.2_/docker/conf.d/celerybeat.conf
arches_containers/template/_6.2_/docker/conf.d/celeryd.conf
arches_containers/template/_6.2_/docker/nginx-config/default.conf
arches_containers/template/_6.2_/docker/nginx-config/default_with_pg_serv.conf
arches_containers-1.0.0.dist-info/licenses/LICENSE.txt
arches_containers-1.0.0.dist-info/METADATA
arches_containers-1.0.0.dist-info/WHEEL
arches_containers-1.0.0.dist-info/entry_points.txt
arches_containers-1.0.0.dist-info/top_level.txt
arches_containers-1.0.0.dist-info/RECORD
