Metadata-Version: 2.4
Name: arches-containers
Version: 1.0.0
Summary: A python developer tool for Arches Project that provides a way to create arches development environments. Supports Arches 6.1 to 8.0 (current development version).
Author-email: Andrew Jones <andrew.jones@historicengland.org.uk>
Maintainer-email: Andrew Jones <andrew.jones@historicengland.org.uk>
License: AGPL-3.0
Project-URL: Repository, https://github.com/HistoricEngland/arches-containers.git
Project-URL: Issues, https://github.com/HistoricEngland/arches-containers/issues
Keywords: arches,development,containers
Classifier: Development Status :: 5 - Production/Stable
Classifier: Intended Audience :: Developers
Classifier: License :: OSI Approved :: GNU Affero General Public License v3
Classifier: Programming Language :: Python :: 3
Classifier: Programming Language :: Python :: 3.9
Classifier: Programming Language :: Python :: 3.10
Classifier: Programming Language :: Python :: 3.11
Classifier: Programming Language :: Python :: 3.12
Classifier: Programming Language :: Python :: 3.13
Requires-Python: >=3.9
License-File: LICENSE.txt
Requires-Dist: python-slugify==7.0.0
Requires-Dist: text-unidecode==1.3
Requires-Dist: rich==13.9.4
Requires-Dist: rich-argparse==1.6.0
Requires-Dist: prettytable==3.12.0
Requires-Dist: pre-commit==3.8.0
Requires-Dist: black==24.4.2
Provides-Extra: dev
Requires-Dist: build; extra == "dev"
Requires-Dist: twine; extra == "dev"
Requires-Dist: pytest; extra == "dev"
Dynamic: license-file
